{
    "title": "Como hacer un vaso multifuncional (caf\u00e9, agua, refesco, jugo, etc......)",
    "description": "Espero te halla gustado este video y si fue as\u00ed reg\u00e1lame un like.",
    "referenceId": "zyjiMrUTvKo",
    "date_created": "1474038879",
    "date_modified": "1486664392",
    "tags": "",
    "sourceId": "4",
    "VIDEO_LENGTH": "SHORT",
    "duration": "184",
    "status": "approved",
    "visibility": "1",
    "video_type": null,
    "main_category": null,
    "sub_category": null,
    "VV_VI": null,
    "CVV_VI": null,
    "engagement_score": null,
    "conversion_score": null,
    "user_id": "0",
    "id": "85322452",
    "loginId": "1758904",
    "entityType": "1",
    "titleTextEncoded": "Como-hacer-un-vaso-multifuncional-caf\u00e9-agua-refesco-jugo-etc",
    "category": "",
    "settings": "",
    "asset": {
        "type": "youtube",
        "thumbnailUrl": "https:\/\/i.ytimg.com\/vi\/zyjiMrUTvKo\/hqdefault.jpg",
        "uploadDate": 1474038879,
        "videoId": "zyjiMrUTvKo",
        "title": "Como hacer un vaso multifuncional (caf\u00e9, agua, refesco, jugo, etc......)",
        "description": "Espero te halla gustado este video y si fue as\u00ed reg\u00e1lame un like.",
        "author": "ALUX GAMER TV PRO",
        "mediaDuration": 184,
        "prettyDuration": "00:03:04",
        "views": "22"
    },
    "transcripts": "",
    "metrics_statistics": null,
    "tvp_profiles": null,
    "tvp_profiles_manual": null,
    "tvp_profiles_maxscore": null,
    "tvp_enhanced_search": null,
    "tvp_enhanced_anti": null,
    "tvp_enhanced_brand": null,
    "tvp_enhanced_video_images": null,
    "tvp_enhanced_transcript": null
}